testing_ash_sdk/__init__.py
testing_ash_sdk-1.0.0.dist-info/METADATA
testing_ash_sdk-1.0.0.dist-info/WHEEL
testing_ash_sdk-1.0.0.dist-info/licenses/LICENSE
testing_ash_sdk-1.0.0.dist-info/RECORD
