Metadata-Version: 2.4
Name: testing-ash-sdk
Version: 1.0.0
Summary: A simple demo SDK
Author: Ash
License-Expression: MIT
License-File: LICENSE
Keywords: demo,sdk,testing-ash
Classifier: Development Status :: 4 - Beta
Classifier: License :: OSI Approved :: MIT License
Classifier: Programming Language :: Python :: 3
Requires-Python: >=3.7
